oauth2_provider/__init__.py
oauth2_provider/admin.py
oauth2_provider/apps.py
oauth2_provider/backends.py
oauth2_provider/compat.py
oauth2_provider/decorators.py
oauth2_provider/exceptions.py
oauth2_provider/forms.py
oauth2_provider/generators.py
oauth2_provider/http.py
oauth2_provider/middleware.py
oauth2_provider/models.py
oauth2_provider/oauth2_backends.py
oauth2_provider/oauth2_validators.py
oauth2_provider/scopes.py
oauth2_provider/settings.py
oauth2_provider/signals.py
oauth2_provider/urls.py
oauth2_provider/validators.py
oauth2_provider/contrib/__init__.py
oauth2_provider/contrib/rest_framework/__init__.py
oauth2_provider/contrib/rest_framework/authentication.py
oauth2_provider/contrib/rest_framework/permissions.py
oauth2_provider/management/__init__.py
oauth2_provider/management/commands/__init__.py
oauth2_provider/management/commands/cleartokens.py
oauth2_provider/management/commands/createapplication.py
oauth2_provider/migrations/0001_initial.py
oauth2_provider/migrations/0002_08_updates.py
oauth2_provider/migrations/0003_auto_20160316_1503.py
oauth2_provider/migrations/0004_auto_20160525_1623.py
oauth2_provider/migrations/0005_auto_20170514_1141.py
oauth2_provider/migrations/0006_auto_20170903_1632.py
oauth2_provider/migrations/0006_auto_20171214_2232.py
oauth2_provider/migrations/0007_application_algorithm.py
oauth2_provider/migrations/0008_idtoken.py
oauth2_provider/migrations/0009_merge_20180606_1314.py
oauth2_provider/migrations/0010_auto_20190406_1805.py
oauth2_provider/migrations/0011_auto_20190413_2007.py
oauth2_provider/migrations/0012_accesstoken_id_token.py
oauth2_provider/migrations/0013_auto_20190816_1714.py
oauth2_provider/migrations/0014_auto_20210510_0935.py
oauth2_provider/migrations/0015_fix_uuid_20210527_1930.py
oauth2_provider/migrations/0016_alter_accesstoken_user_alter_application_user_and_more.py
oauth2_provider/migrations/__init__.py
oauth2_provider/templates/oauth2_provider/application_confirm_delete.html
geonode_oauth_toolkit-2.2.2.1.dist-info/AUTHORS
geonode_oauth_toolkit-2.2.2.1.dist-info/LICENSE
geonode_oauth_toolkit-2.2.2.1.dist-info/METADATA
geonode_oauth_toolkit-2.2.2.1.dist-info/WHEEL
geonode_oauth_toolkit-2.2.2.1.dist-info/top_level.txt
geonode_oauth_toolkit-2.2.2.1.dist-info/RECORD
