Metadata-Version: 2.1
Name: geonode-oauth-toolkit
Version: 2.2.2.1
Summary: OAuth2 Provider for Django/GeoNode
Home-page: https://github.com/GeoNode/geonode-oauth-toolkit
Author: Federico Frenguelli, Massimiliano Pippi, Alessio Fabiani
Author-email: synasius@gmail.com
Keywords: django,oauth,oauth2,oauthlib
Classifier: Development Status :: 5 - Production/Stable
Classifier: Environment :: Web Environment
Classifier: Framework :: Django
Classifier: Framework :: Django :: 2.2
Classifier: Framework :: Django :: 3.1
Classifier: Framework :: Django :: 3.2
Classifier: Intended Audience :: Developers
Classifier: License :: OSI Approved :: BSD License
Classifier: Operating System :: OS Independent
Classifier: Programming Language :: Python :: 3
Classifier: Programming Language :: Python :: 3.6
Classifier: Programming Language :: Python :: 3.7
Classifier: Programming Language :: Python :: 3.8
Classifier: Programming Language :: Python :: 3.9
Classifier: Topic :: Internet :: WWW/HTTP
License-File: LICENSE
License-File: AUTHORS
Requires-Dist: django >=2.2
Requires-Dist: requests >=2.13.0
Requires-Dist: oauthlib >=3.1.0
Requires-Dist: jwcrypto >=0.8.0
Requires-Dist: six
